MANIFEST.in
README.rst
setup.py
Products/__init__.py
Products.ZSQLiteDA.egg-info/PKG-INFO
Products.ZSQLiteDA.egg-info/SOURCES.txt
Products.ZSQLiteDA.egg-info/dependency_links.txt
Products.ZSQLiteDA.egg-info/entry_points.txt
Products.ZSQLiteDA.egg-info/namespace_packages.txt
Products.ZSQLiteDA.egg-info/not-zip-safe
Products.ZSQLiteDA.egg-info/requires.txt
Products.ZSQLiteDA.egg-info/top_level.txt
Products/ZSQLiteDA/DA.py
Products/ZSQLiteDA/__init__.py
Products/ZSQLiteDA/db.py
Products/ZSQLiteDA/dtml/browse.dtml
Products/ZSQLiteDA/dtml/connectionAdd.dtml
Products/ZSQLiteDA/dtml/connectionEdit.dtml
Products/ZSQLiteDA/dtml/connectionStatus.dtml
Products/ZSQLiteDA/images/DBAdapterFolder_icon.gif
Products/ZSQLiteDA/images/table.gif