Metadata-Version: 1.1
Name: Products.ZSQLiteDA
Version: 0.8.0
Summary: SQLite database adapter for Zope4
Home-page: https://github.com/nakagami/Products.ZSQLiteDA
Author: Hajime Nakagami
Author-email: nakagami@gmail.com
License: ZPL
Keywords: SQLite
Platform: UNKNOWN
Classifier: Programming Language :: Python
Classifier: Framework :: Zope :: 4
Classifier: Framework :: Zope :: 5
Classifier: License :: OSI Approved :: Zope Public License
